markkc_siunits/__init__.py
markkc_siunits/main.py
markkc_siunits-0.0.8.dist-info/LICENSE
markkc_siunits-0.0.8.dist-info/METADATA
markkc_siunits-0.0.8.dist-info/WHEEL
markkc_siunits-0.0.8.dist-info/top_level.txt
markkc_siunits-0.0.8.dist-info/RECORD
